gultron/__init__.py
gultron/cmd.py
gultron/commit_message.py
gultron/logs.py
gultron/run.py
gultron/utils.py
gultron-1.2.2.dist-info/LICENSE
gultron-1.2.2.dist-info/METADATA
gultron-1.2.2.dist-info/WHEEL
gultron-1.2.2.dist-info/entry_points.txt
gultron-1.2.2.dist-info/RECORD
