Metadata-Version: 2.1
Name: gultron
Version: 1.2.2
Summary: AI-powered Git commit message generator.
Author: Mahmoud Emad
Author-email: mahmmoud.hassanein@gmail.com
Requires-Python: >=3.12,<4.0
Classifier: Programming Language :: Python :: 3
Classifier: Programming Language :: Python :: 3.12
Classifier: Programming Language :: Python :: 3.13
Requires-Dist: colorlog (>=6.9.0,<7.0.0)
Requires-Dist: gitpython (>=3.1.43,<4.0.0)
Requires-Dist: google-generativeai (>=0.8.3,<0.9.0)
Requires-Dist: grpcio (==1.60.1)
Requires-Dist: pyfiglet (>=1.0.2,<2.0.0)
Requires-Dist: pyperclip (>=1.9.0,<2.0.0)
Requires-Dist: pytest (>=8.3.4,<9.0.0)
Requires-Dist: python-decouple (>=3.8,<4.0)
Requires-Dist: shiv (>=1.0.8,<2.0.0)
